{
  "matches": [
    {
      "db_id": "283824f9-4e87-463d-8d28-71ba0edd51fa",
      "full_name": "SheenBee Oh",
      "english_name": "SheenBee",
      "student_id": "780",
      "grade": "6"
    },
    {
      "db_id": "9983a860-9917-4235-990e-85d97a40930e",
      "full_name": "Camry Tobias",
      "english_name": "Camry",
      "student_id": "1199",
      "grade": "7"
    },
    {
      "db_id": "0eecdec8-f467-4bb5-b6f0-956871a627dd",
      "full_name": "Jayrielle Miriam Mirasol",
      "english_name": "Jayrielle",
      "student_id": "1065",
      "grade": "8"
    },
    {
      "db_id": "e14d8495-1592-4d08-8e1c-c5f419d93aa1",
      "full_name": "Ayra Mari Dantis",
      "english_name": "Ayra",
      "student_id": "1208",
      "grade": "9"
    },
    {
      "db_id": "00e6f84f-4169-485a-85e8-8f3de0b29d9b",
      "full_name": "Seokyung Joo",
      "english_name": "Luna",
      "student_id": "1181",
      "grade": "9"
    },
    {
      "db_id": "0940416d-e41e-4b3e-9c83-18d9f7c58a70",
      "full_name": "Gyuri Lim",
      "english_name": "Gyuri",
      "student_id": "1227",
      "grade": "9"
    },
    {
      "db_id": "76a9445b-f64a-495f-8665-8203b8fe80b5",
      "full_name": "Jaehyun Choi",
      "english_name": "Jaehyun",
      "student_id": "1167",
      "grade": "10"
    },
    {
      "db_id": "72d8939a-8ace-437f-84cc-73bcac45242e",
      "full_name": "Riwon Kim",
      "english_name": "Riwon",
      "student_id": "1073",
      "grade": "10"
    },
    {
      "db_id": "b3f9bef4-6916-4102-896a-70d0e3a06eb8",
      "full_name": "Sieun Kwon",
      "english_name": "Emily",
      "student_id": "837",
      "grade": "10"
    },
    {
      "db_id": "76e21f92-562a-4a85-bf59-612e3b0b8865",
      "full_name": "Jasmine Kelly Line",
      "english_name": "Jas",
      "student_id": "528",
      "grade": "10"
    },
    {
      "db_id": "4244139a-2806-4b30-9c5a-a28ec91c281b",
      "full_name": "Subhin Oh",
      "english_name": "Amy",
      "student_id": "1213",
      "grade": "10"
    },
    {
      "db_id": "2160b0dc-045a-4f33-9915-c1b8c46e83e5",
      "full_name": "Jooeun Park",
      "english_name": "Julia",
      "student_id": "1192",
      "grade": "10"
    },
    {
      "db_id": "5d04e081-4d73-4b69-a654-632fff2cceb7",
      "full_name": "Seoyeon Park",
      "english_name": "Seoyeon",
      "student_id": "1117",
      "grade": "10"
    },
    {
      "db_id": "fe6a54c6-fe8f-4440-900b-1639c440a34b",
      "full_name": "Serin Park",
      "english_name": "Serin",
      "student_id": "760",
      "grade": "10"
    },
    {
      "db_id": "29993a12-33fb-44ce-96df-13350be23106",
      "full_name": "Seojin joug",
      "english_name": "Seojin",
      "student_id": "959",
      "grade": "11"
    },
    {
      "db_id": "d6720f25-cb44-4e1b-b701-8f583f4c0d54",
      "full_name": "Bat-Ochir Odmandakh",
      "english_name": "Ochko",
      "student_id": "921",
      "grade": "11"
    }
  ],
  "name_mismatches": [
    {
      "db_id": "d1553c88-8e96-4cd4-9b37-1f1ca5b221e2",
      "db_full_name": "Gabriel Albrecht",
      "db_english_name": "Gabriel",
      "ml_full_name": "Gabriel Alexander Albrecht",
      "ml_english_name": "Gabriel",
      "ml_student_id": "1138",
      "grade": "6"
    },
    {
      "db_id": "82f42c8d-4dd5-4ccf-aaca-5e9ac1668167",
      "db_full_name": "Kyung,Seryn",
      "db_english_name": "Seryn",
      "ml_full_name": "Seryn Kyung",
      "ml_english_name": "Seryn",
      "ml_student_id": "1111",
      "grade": "6"
    },
    {
      "db_id": "2c405160-b725-4cf7-a72c-ec94906eace6",
      "db_full_name": "Myra Williams",
      "db_english_name": "Myra",
      "ml_full_name": "Myra James Williams",
      "ml_english_name": "Myra",
      "ml_student_id": "875",
      "grade": "6"
    },
    {
      "db_id": "3ab2cbba-ae54-4cda-b6da-2a2fc9fbd46f",
      "db_full_name": "Jason Go Sanghyuk",
      "db_english_name": "Jason",
      "ml_full_name": "Sanghyuk Go",
      "ml_english_name": "Jason",
      "ml_student_id": "948",
      "grade": "7"
    },
    {
      "db_id": "ded472a1-6405-4422-8aa4-a603295dde54",
      "db_full_name": "Benjamin Garland",
      "db_english_name": "Benjamin",
      "ml_full_name": "Benjamin Jake Osabel Garland",
      "ml_english_name": "Benjamin",
      "ml_student_id": "432",
      "grade": "8"
    },
    {
      "db_id": "52b6a305-9727-45cb-8e3b-6ec098d20780",
      "db_full_name": "Azra Nez Gabrielle P.",
      "db_english_name": "Azra",
      "ml_full_name": "Azra Nez Gabrielle Perez Lumbu-an",
      "ml_english_name": "Azra",
      "ml_student_id": "951",
      "grade": "8"
    },
    {
      "db_id": "a337c653-8973-4bff-bc28-1fd2a02d99c2",
      "db_full_name": "Jacob Park",
      "db_english_name": "Jacob",
      "ml_full_name": "Jon Jacob Dayrit Smith",
      "ml_english_name": "Jacob",
      "ml_student_id": "362",
      "grade": "8"
    },
    {
      "db_id": "b5af66fe-a958-475a-955e-9144231ac75e",
      "db_full_name": "Aryanna Destiny Wegner",
      "db_english_name": "Aryanna",
      "ml_full_name": "Aryanna Destiny Portugaliza Wegner",
      "ml_english_name": "Aryanna",
      "ml_student_id": "465",
      "grade": "8"
    },
    {
      "db_id": "90ef100c-27ec-4c44-9dcf-9be93d874f75",
      "db_full_name": "Huang, Shiyu",
      "db_english_name": "Kevin",
      "ml_full_name": "Minsung Kim",
      "ml_english_name": "Kevin",
      "ml_student_id": "916",
      "grade": "9"
    },
    {
      "db_id": "7c2ba891-7eaa-4672-9d01-4d8a347dd4c7",
      "db_full_name": "Timo Frey",
      "db_english_name": "Timo",
      "ml_full_name": "Timo Wendelin Frey",
      "ml_english_name": "Timo",
      "ml_student_id": "1211",
      "grade": "10"
    },
    {
      "db_id": "90ef100c-27ec-4c44-9dcf-9be93d874f75",
      "db_full_name": "Huang, Shiyu",
      "db_english_name": "Kevin",
      "ml_full_name": "Shiyu Huang",
      "ml_english_name": "Kevin",
      "ml_student_id": "1014",
      "grade": "10"
    },
    {
      "db_id": "7a3a5047-7477-433f-886c-08657b1298dd",
      "db_full_name": "SHINWOOK",
      "db_english_name": "SHINWOOK",
      "ml_full_name": "Shinwook Kim",
      "ml_english_name": "Shinwook",
      "ml_student_id": "886",
      "grade": "10"
    },
    {
      "db_id": "9b6b75ff-9023-4c17-bc95-7a53aa68dd1e",
      "db_full_name": "Kim, Youeun",
      "db_english_name": "Anne",
      "ml_full_name": "Youeun Kim",
      "ml_english_name": "Anne",
      "ml_student_id": "1168",
      "grade": "10"
    },
    {
      "db_id": "2ac4db47-ba4d-4fe0-b1a9-535148229896",
      "db_full_name": "Lee Seungwon",
      "db_english_name": "Daven",
      "ml_full_name": "Seungwon Lee",
      "ml_english_name": "Daven",
      "ml_student_id": "1116",
      "grade": "10"
    },
    {
      "db_id": "eb8c255b-c7a9-4145-b0b8-2777fa1de738",
      "db_full_name": "Park Gahyun",
      "db_english_name": "Katie",
      "ml_full_name": "Gahyun Park",
      "ml_english_name": "Katie",
      "ml_student_id": "1085",
      "grade": "11"
    },
    {
      "db_id": "90ef100c-27ec-4c44-9dcf-9be93d874f75",
      "db_full_name": "Huang, Shiyu",
      "db_english_name": "Kevin",
      "ml_full_name": "Siyue Chen",
      "ml_english_name": "Kevin",
      "ml_student_id": "622",
      "grade": "12"
    },
    {
      "db_id": "0665fa71-f155-4090-833b-6b11a359ba58",
      "db_full_name": "Sean Park",
      "db_english_name": "Sean",
      "ml_full_name": "Sean Lee",
      "ml_english_name": "Sean",
      "ml_student_id": "975",
      "grade": "12"
    },
    {
      "db_id": "0665fa71-f155-4090-833b-6b11a359ba58",
      "db_full_name": "Sean Park",
      "db_english_name": "Sean",
      "ml_full_name": "Sieon Park",
      "ml_english_name": "Sean",
      "ml_student_id": "977",
      "grade": "12"
    }
  ],
  "not_in_db": [
    {
      "student_id": "1139",
      "official_name": "Aldana, Yxabella",
      "full_name": "Yxabella Aldana",
      "korean_name": "",
      "english_name": "Bella",
      "grade": "6",
      "gender": "Female"
    },
    {
      "student_id": "1050",
      "official_name": "Cho, Soojeong Diaz",
      "full_name": "Soojeong Diaz Cho",
      "korean_name": "",
      "english_name": "Kristal",
      "grade": "6",
      "gender": "Female"
    },
    {
      "student_id": "1110",
      "official_name": "Hong, Seokwoo",
      "full_name": "Seokwoo Hong",
      "korean_name": "",
      "english_name": "Seokwoo",
      "grade": "6",
      "gender": "Male"
    },
    {
      "student_id": "874",
      "official_name": "Ko, Woohyun",
      "full_name": "Woohyun Ko",
      "korean_name": "",
      "english_name": "Rex",
      "grade": "6",
      "gender": "Male"
    },
    {
      "student_id": "1197",
      "official_name": "Lee, Woojae",
      "full_name": "Woojae Lee",
      "korean_name": "",
      "english_name": "Woojae",
      "grade": "6",
      "gender": "Male"
    },
    {
      "student_id": "1194",
      "official_name": "Ma, Quang Bao",
      "full_name": "Quang Bao Ma",
      "korean_name": "",
      "english_name": "David",
      "grade": "6",
      "gender": "Male"
    },
    {
      "student_id": "1140",
      "official_name": "Mateo, Vhretchard",
      "full_name": "Vhretchard Mateo",
      "korean_name": "",
      "english_name": "Chard",
      "grade": "6",
      "gender": "Male"
    },
    {
      "student_id": "759",
      "official_name": "Park, Rahee",
      "full_name": "Rahee Park",
      "korean_name": "",
      "english_name": "Rahee",
      "grade": "6",
      "gender": "Female"
    },
    {
      "student_id": "493",
      "official_name": "Park, Sia",
      "full_name": "Sia Park",
      "korean_name": "",
      "english_name": "Sia",
      "grade": "6",
      "gender": "Female"
    },
    {
      "student_id": "504",
      "official_name": "Verma, Ayaan",
      "full_name": "Ayaan Verma",
      "korean_name": "",
      "english_name": "Ayaan",
      "grade": "6",
      "gender": "Male"
    },
    {
      "student_id": "1120",
      "official_name": "An, Sua",
      "full_name": "Sua An",
      "korean_name": "",
      "english_name": "Sua",
      "grade": "7",
      "gender": "Female"
    },
    {
      "student_id": "1173",
      "official_name": "Chang, Seowoo",
      "full_name": "Seowoo Chang",
      "korean_name": "",
      "english_name": "Lia",
      "grade": "7",
      "gender": "Female"
    },
    {
      "student_id": "1200",
      "official_name": "Choi, Jiung",
      "full_name": "Jiung Choi",
      "korean_name": "",
      "english_name": "Jaime",
      "grade": "7",
      "gender": "Male"
    },
    {
      "student_id": "1051",
      "official_name": "Chopra, Adi",
      "full_name": "Adi Chopra",
      "korean_name": "",
      "english_name": "Adi",
      "grade": "7",
      "gender": "Male"
    },
    {
      "student_id": "1201",
      "official_name": "Corpuz, Macy Margaux",
      "full_name": "Macy Margaux Corpuz",
      "korean_name": "",
      "english_name": "Margaux",
      "grade": "7",
      "gender": ""
    },
    {
      "student_id": "1202",
      "official_name": "Dedil, Erika Amor",
      "full_name": "Erika Amor Dedil",
      "korean_name": "",
      "english_name": "Erika",
      "grade": "7",
      "gender": "Female"
    },
    {
      "student_id": "846",
      "official_name": "Headley, Cataleyna Sophia",
      "full_name": "Cataleyna Sophia Headley",
      "korean_name": "",
      "english_name": "Sophia",
      "grade": "7",
      "gender": "Female"
    },
    {
      "student_id": "1112",
      "official_name": "Hong, Seokju",
      "full_name": "Seokju Hong",
      "korean_name": "",
      "english_name": "Justin",
      "grade": "7",
      "gender": "Male"
    },
    {
      "student_id": "1052",
      "official_name": "Kim, Huije",
      "full_name": "Huije Kim",
      "korean_name": "",
      "english_name": "Jerome",
      "grade": "7",
      "gender": "Male"
    },
    {
      "student_id": "1176",
      "official_name": "Kim, Kyuhyeon",
      "full_name": "Kyuhyeon Kim",
      "korean_name": "",
      "english_name": "Evan",
      "grade": "7",
      "gender": "Male"
    },
    {
      "student_id": "1113",
      "official_name": "Kyung, Suryn",
      "full_name": "Suryn Kyung",
      "korean_name": "",
      "english_name": "Suryn",
      "grade": "7",
      "gender": "Female"
    },
    {
      "student_id": "1052",
      "official_name": "Lee, Nayeong",
      "full_name": "Nayeong Lee",
      "korean_name": "",
      "english_name": "Nayeong",
      "grade": "7",
      "gender": "Female"
    },
    {
      "student_id": "1174",
      "official_name": "Lee, Jeongwon",
      "full_name": "Jeongwon Lee",
      "korean_name": "",
      "english_name": "",
      "grade": "7",
      "gender": "Male"
    },
    {
      "student_id": "1141",
      "official_name": "Magat, Chrystelle",
      "full_name": "Chrystelle Magat",
      "korean_name": "",
      "english_name": "Chrystelle",
      "grade": "7",
      "gender": "Female"
    },
    {
      "student_id": "1053",
      "official_name": "Park, Jacob Leejun",
      "full_name": "Jacob Leejun Park",
      "korean_name": "",
      "english_name": "",
      "grade": "7",
      "gender": "Male"
    },
    {
      "student_id": "1177",
      "official_name": "Park, Juwon",
      "full_name": "Juwon Park",
      "korean_name": "",
      "english_name": "",
      "grade": "7",
      "gender": "Male"
    },
    {
      "student_id": "1198",
      "official_name": "Saburdo, Eliana",
      "full_name": "Eliana Saburdo",
      "korean_name": "",
      "english_name": "",
      "grade": "7",
      "gender": "Female"
    },
    {
      "student_id": "879",
      "official_name": "Shin, Biya",
      "full_name": "Biya Shin",
      "korean_name": "",
      "english_name": "Biya",
      "grade": "7",
      "gender": "Female"
    },
    {
      "student_id": "1175",
      "official_name": "Song, Jiyeon",
      "full_name": "Jiyeon Song",
      "korean_name": "",
      "english_name": "Ji Yeon",
      "grade": "7",
      "gender": "Female"
    },
    {
      "student_id": "915",
      "official_name": "Tseng, Li-An",
      "full_name": "Li-An Tseng",
      "korean_name": "",
      "english_name": "Li-An",
      "grade": "7",
      "gender": "Male"
    },
    {
      "student_id": "1178",
      "official_name": "Wang, Chi-Wen",
      "full_name": "Chi-Wen Wang",
      "korean_name": "",
      "english_name": "",
      "grade": "7",
      "gender": "Female"
    },
    {
      "student_id": "1203",
      "official_name": "Bonoyer, Alliah Michelle",
      "full_name": "Alliah Michelle Bonoyer",
      "korean_name": "",
      "english_name": "",
      "grade": "8",
      "gender": "Female"
    },
    {
      "student_id": "1204",
      "official_name": "Caminero Obregon, Irene",
      "full_name": "Irene Caminero Obregon",
      "korean_name": "",
      "english_name": "",
      "grade": "8",
      "gender": "Female"
    },
    {
      "student_id": "1205",
      "official_name": "Corkery, Logan Maurice",
      "full_name": "Logan Maurice Corkery",
      "korean_name": "",
      "english_name": "Logan",
      "grade": "8",
      "gender": "Male"
    },
    {
      "student_id": "1098",
      "official_name": "Cho, Yeonkyu",
      "full_name": "Yeonkyu Cho",
      "korean_name": "",
      "english_name": "Atom",
      "grade": "8",
      "gender": "Male"
    },
    {
      "student_id": "1054",
      "official_name": "Choi, Sunyou",
      "full_name": "Sunyou Choi",
      "korean_name": "",
      "english_name": "",
      "grade": "8",
      "gender": "Female"
    },
    {
      "student_id": "1056",
      "official_name": "Dayrit, Timothy Jefferson",
      "full_name": "Timothy Jefferson Dayrit",
      "korean_name": "",
      "english_name": "",
      "grade": "8",
      "gender": "Male"
    },
    {
      "student_id": "1058",
      "official_name": "Jeong, Hyunyoung",
      "full_name": "Hyunyoung Jeong",
      "korean_name": "",
      "english_name": "Tom",
      "grade": "8",
      "gender": "Male"
    },
    {
      "student_id": "1165",
      "official_name": "Kang, Ryukeon",
      "full_name": "Ryukeon Kang",
      "korean_name": "",
      "english_name": "Yogan",
      "grade": "8",
      "gender": "Male"
    },
    {
      "student_id": "517",
      "official_name": "Kim, Ga-on",
      "full_name": "Ga-on Kim",
      "korean_name": "",
      "english_name": "Lydia",
      "grade": "8",
      "gender": "Female"
    },
    {
      "student_id": "1059",
      "official_name": "Kim, Hyeyun",
      "full_name": "Hyeyun Kim",
      "korean_name": "",
      "english_name": "Bella",
      "grade": "8",
      "gender": "Female"
    },
    {
      "student_id": "1179",
      "official_name": "Kim, Kyuri",
      "full_name": "Kyuri Kim",
      "korean_name": "",
      "english_name": "Selena",
      "grade": "8",
      "gender": "Female"
    },
    {
      "student_id": "1126",
      "official_name": "Kim, Taegeon",
      "full_name": "Taegeon Kim",
      "korean_name": "",
      "english_name": "Eden",
      "grade": "8",
      "gender": "Male"
    },
    {
      "student_id": "1060",
      "official_name": "Kim, Seunghu",
      "full_name": "Seunghu Kim",
      "korean_name": "",
      "english_name": "Cris",
      "grade": "8",
      "gender": "Male"
    },
    {
      "student_id": "836",
      "official_name": "Kwon, Sihyun",
      "full_name": "Sihyun Kwon",
      "korean_name": "",
      "english_name": "Lowell",
      "grade": "8",
      "gender": "Female"
    },
    {
      "student_id": "1062",
      "official_name": "Lee, Halin",
      "full_name": "Halin Lee",
      "korean_name": "",
      "english_name": "",
      "grade": "8",
      "gender": "Female"
    },
    {
      "student_id": "1127",
      "official_name": "Lee, Jeongmo",
      "full_name": "Jeongmo Lee",
      "korean_name": "",
      "english_name": "",
      "grade": "8",
      "gender": "Male"
    },
    {
      "student_id": "1114",
      "official_name": "Lee, Ryan Agustin",
      "full_name": "Ryan Agustin Lee",
      "korean_name": "",
      "english_name": "",
      "grade": "8",
      "gender": "Male"
    },
    {
      "student_id": "1206",
      "official_name": "Ong, Jazlynne Nina",
      "full_name": "Jazlynne Nina Ong",
      "korean_name": "",
      "english_name": "",
      "grade": "8",
      "gender": "Female"
    },
    {
      "student_id": "397",
      "official_name": "Park, Leah",
      "full_name": "Leah Park",
      "korean_name": "",
      "english_name": "Leah",
      "grade": "8",
      "gender": "Female"
    },
    {
      "student_id": "1207",
      "official_name": "Saburdo, Alexandra",
      "full_name": "Alexandra Saburdo",
      "korean_name": "",
      "english_name": "",
      "grade": "8",
      "gender": "Female"
    },
    {
      "student_id": "1180",
      "official_name": "Seo, Seongyun",
      "full_name": "Seongyun Seo",
      "korean_name": "",
      "english_name": "",
      "grade": "8",
      "gender": "Male"
    },
    {
      "student_id": "776",
      "official_name": "Stanley, Gel Emrie Pedrito",
      "full_name": "Gel Emrie Pedrito Stanley",
      "korean_name": "",
      "english_name": "Gel Emrie",
      "grade": "8",
      "gender": "Female"
    },
    {
      "student_id": "834",
      "official_name": "Yoon, Jaewoong",
      "full_name": "Jaewoong Yoon",
      "korean_name": "",
      "english_name": "Jaewoong",
      "grade": "8",
      "gender": "Male"
    },
    {
      "student_id": "487",
      "official_name": "Adarlo, Chloe Liz",
      "full_name": "Chloe Liz Adarlo",
      "korean_name": "",
      "english_name": "Chloe",
      "grade": "9",
      "gender": "Female"
    },
    {
      "student_id": "999",
      "official_name": "Chang, Seoyoon",
      "full_name": "Seoyoon Chang",
      "korean_name": "",
      "english_name": "Lydia",
      "grade": "9",
      "gender": "Female"
    },
    {
      "student_id": "1166",
      "official_name": "Choi, Jiyoo",
      "full_name": "Jiyoo Choi",
      "korean_name": "",
      "english_name": "Wendy",
      "grade": "9",
      "gender": "Female"
    },
    {
      "student_id": "1067",
      "official_name": "Jang, Rahee",
      "full_name": "Rahee Jang",
      "korean_name": "",
      "english_name": "",
      "grade": "9",
      "gender": "Female"
    },
    {
      "student_id": "996",
      "official_name": "Lee, Daeun",
      "full_name": "Daeun Lee",
      "korean_name": "",
      "english_name": "Jessica",
      "grade": "9",
      "gender": "Female"
    },
    {
      "student_id": "1182",
      "official_name": "Wang, Hao-Ming",
      "full_name": "Hao-Ming Wang",
      "korean_name": "",
      "english_name": "",
      "grade": "9",
      "gender": "Male"
    },
    {
      "student_id": "1115",
      "official_name": "Ahn, Jaein",
      "full_name": "Jaein Ahn",
      "korean_name": "",
      "english_name": "",
      "grade": "10",
      "gender": "Female"
    },
    {
      "student_id": "387",
      "official_name": "Altangerel, Anir",
      "full_name": "Anir Altangerel",
      "korean_name": "",
      "english_name": "Annie A",
      "grade": "10",
      "gender": "Female"
    },
    {
      "student_id": "1210",
      "official_name": "Corpuz, Sophia Juanita Noreve",
      "full_name": "Sophia Juanita Noreve Corpuz",
      "korean_name": "",
      "english_name": "Sophia",
      "grade": "10",
      "gender": "Female"
    },
    {
      "student_id": "175",
      "official_name": "Cruz, John Ignacio Pamintuan",
      "full_name": "John Ignacio Pamintuan Cruz",
      "korean_name": "",
      "english_name": "Nash",
      "grade": "10",
      "gender": "Male"
    },
    {
      "student_id": "998",
      "official_name": "Ha, Taehoon",
      "full_name": "Taehoon Ha",
      "korean_name": "",
      "english_name": "Kyle",
      "grade": "10",
      "gender": "Male"
    },
    {
      "student_id": "196",
      "official_name": "Hickey, Michael Edward",
      "full_name": "Michael Edward Hickey",
      "korean_name": "",
      "english_name": "Michael",
      "grade": "10",
      "gender": "Male"
    },
    {
      "student_id": "1072",
      "official_name": "Hong, Hyongju",
      "full_name": "Hyongju Hong",
      "korean_name": "",
      "english_name": "Joshua",
      "grade": "10",
      "gender": "Male"
    },
    {
      "student_id": "887",
      "official_name": "Ko, Woojin",
      "full_name": "Woojin Ko",
      "korean_name": "",
      "english_name": "Edward",
      "grade": "10",
      "gender": "Male"
    },
    {
      "student_id": "1193",
      "official_name": "Lee, Dayeon",
      "full_name": "Dayeon Lee",
      "korean_name": "",
      "english_name": "Sally",
      "grade": "10",
      "gender": "Female"
    },
    {
      "student_id": "1212",
      "official_name": "Lerio, Jonathan Michael",
      "full_name": "Jonathan Michael Lerio",
      "korean_name": "",
      "english_name": "",
      "grade": "10",
      "gender": "Male"
    },
    {
      "student_id": "1169",
      "official_name": "Li, Jhih-Yun",
      "full_name": "Jhih-Yun Li",
      "korean_name": "",
      "english_name": "Annabelle",
      "grade": "10",
      "gender": "Female"
    },
    {
      "student_id": "1092",
      "official_name": "Nablo Jr., Manuel",
      "full_name": "Manuel Nablo Jr.",
      "korean_name": "",
      "english_name": "Manuel",
      "grade": "10",
      "gender": "Male"
    },
    {
      "student_id": "1214",
      "official_name": "Papango, Cyrus Dave",
      "full_name": "Cyrus Dave Papango",
      "korean_name": "",
      "english_name": "Cyruz",
      "grade": "10",
      "gender": "Male"
    },
    {
      "student_id": "1183",
      "official_name": "Seo, Jeongwoo",
      "full_name": "Jeongwoo Seo",
      "korean_name": "",
      "english_name": "",
      "grade": "10",
      "gender": "Female"
    },
    {
      "student_id": "1215",
      "official_name": "Son, Ayeong",
      "full_name": "Ayeong Son",
      "korean_name": "",
      "english_name": "Lucy",
      "grade": "10",
      "gender": "Female"
    },
    {
      "student_id": "1118",
      "official_name": "Tran, Ngoc Han",
      "full_name": "Ngoc Han Tran",
      "korean_name": "",
      "english_name": "Han",
      "grade": "10",
      "gender": "Female"
    },
    {
      "student_id": "835",
      "official_name": "Yoon, Taewoong",
      "full_name": "Taewoong Yoon",
      "korean_name": "",
      "english_name": "Taewoong",
      "grade": "10",
      "gender": "Male"
    },
    {
      "student_id": "1196",
      "official_name": "Yu, Seoyeong",
      "full_name": "Seoyeong Yu",
      "korean_name": "",
      "english_name": "Sally",
      "grade": "10",
      "gender": "Female"
    },
    {
      "student_id": "1216",
      "official_name": "Zaicek, Kendra Jeanelle",
      "full_name": "Kendra Jeanelle Zaicek",
      "korean_name": "",
      "english_name": "",
      "grade": "10",
      "gender": "Female"
    },
    {
      "student_id": "1191",
      "official_name": "Bui, Phuoc Nhan",
      "full_name": "Phuoc Nhan Bui",
      "korean_name": "",
      "english_name": "Heri B",
      "grade": "11",
      "gender": "Male"
    },
    {
      "student_id": "1075",
      "official_name": "Du, Tommy",
      "full_name": "Tommy Du",
      "korean_name": "",
      "english_name": "Tommy",
      "grade": "11",
      "gender": "Male"
    },
    {
      "student_id": "958",
      "official_name": "Joug, Seojun",
      "full_name": "Seojun Joug",
      "korean_name": "",
      "english_name": "Jun",
      "grade": "11",
      "gender": "Male"
    },
    {
      "student_id": "894",
      "official_name": "Kim, Yijoon",
      "full_name": "Yijoon Kim",
      "korean_name": "",
      "english_name": "Caleb",
      "grade": "11",
      "gender": "Male"
    },
    {
      "student_id": "1079",
      "official_name": "Kwon, Dohee",
      "full_name": "Dohee Kwon",
      "korean_name": "",
      "english_name": "",
      "grade": "11",
      "gender": "Female"
    },
    {
      "student_id": "1001",
      "official_name": "Kwon, Heemin",
      "full_name": "Heemin Kwon",
      "korean_name": "",
      "english_name": "",
      "grade": "11",
      "gender": "Male"
    },
    {
      "student_id": "1093",
      "official_name": "Lee, Haon",
      "full_name": "Haon Lee",
      "korean_name": "",
      "english_name": "",
      "grade": "11",
      "gender": "Female"
    },
    {
      "student_id": "1080",
      "official_name": "Lee, Naeun",
      "full_name": "Naeun Lee",
      "korean_name": "",
      "english_name": "",
      "grade": "11",
      "gender": "Female"
    },
    {
      "student_id": "997",
      "official_name": "Lee, Seungmin",
      "full_name": "Seungmin Lee",
      "korean_name": "",
      "english_name": "Tony",
      "grade": "11",
      "gender": "Male"
    },
    {
      "student_id": "1081",
      "official_name": "Marzan, Czyrel",
      "full_name": "Czyrel Marzan",
      "korean_name": "",
      "english_name": "",
      "grade": "11",
      "gender": "Female"
    },
    {
      "student_id": "1082",
      "official_name": "Mirasol, John Marcial",
      "full_name": "John Marcial Mirasol",
      "korean_name": "",
      "english_name": "",
      "grade": "11",
      "gender": "Male"
    },
    {
      "student_id": "166",
      "official_name": "Mustafa, Precious Angelica",
      "full_name": "Precious Angelica Mustafa",
      "korean_name": "",
      "english_name": "Angel",
      "grade": "11",
      "gender": "Female"
    },
    {
      "student_id": "1083",
      "official_name": "Park, Byeongjun",
      "full_name": "Byeongjun Park",
      "korean_name": "",
      "english_name": "Andy",
      "grade": "11",
      "gender": "Male"
    },
    {
      "student_id": "992",
      "official_name": "Park, Jiwon",
      "full_name": "Jiwon Park",
      "korean_name": "",
      "english_name": "",
      "grade": "11",
      "gender": "Female"
    },
    {
      "student_id": "920",
      "official_name": "Park, Yunseo",
      "full_name": "Yunseo Park",
      "korean_name": "",
      "english_name": "Sia",
      "grade": "11",
      "gender": "Female"
    },
    {
      "student_id": "1091",
      "official_name": "Sarinas, Mara-Alexandria Cortes",
      "full_name": "Mara-Alexandria Cortes Sarinas",
      "korean_name": "",
      "english_name": "Mara",
      "grade": "11",
      "gender": "Female"
    },
    {
      "student_id": "1217",
      "official_name": "An, Yujun",
      "full_name": "Yujun An",
      "korean_name": "",
      "english_name": "",
      "grade": "12",
      "gender": "Male"
    },
    {
      "student_id": "895",
      "official_name": "David, Christian Dylan Quiambao",
      "full_name": "Christian Dylan Quiambao David",
      "korean_name": "",
      "english_name": "Christian",
      "grade": "12",
      "gender": "Male"
    },
    {
      "student_id": "973",
      "official_name": "Go, Jiyeon",
      "full_name": "Jiyeon Go",
      "korean_name": "",
      "english_name": "Katy",
      "grade": "12",
      "gender": "Female"
    },
    {
      "student_id": "974",
      "official_name": "Hong, Seungju",
      "full_name": "Seungju Hong",
      "korean_name": "",
      "english_name": "Bryan",
      "grade": "12",
      "gender": "Male"
    },
    {
      "student_id": "440",
      "official_name": "Kim, Minjun",
      "full_name": "Minjun Kim",
      "korean_name": "",
      "english_name": "Jun",
      "grade": "12",
      "gender": "Male"
    },
    {
      "student_id": "838",
      "official_name": "Kwon, Sion",
      "full_name": "Sion Kwon",
      "korean_name": "",
      "english_name": "Jessica",
      "grade": "12",
      "gender": "Female"
    },
    {
      "student_id": "896",
      "official_name": "Lee, Soyeon",
      "full_name": "Soyeon Lee",
      "korean_name": "",
      "english_name": "Soyeon",
      "grade": "12",
      "gender": "Female"
    },
    {
      "student_id": "976",
      "official_name": "Park, Jinseo",
      "full_name": "Jinseo Park",
      "korean_name": "",
      "english_name": "Jinseo",
      "grade": "12",
      "gender": "Female"
    },
    {
      "student_id": "1190",
      "official_name": "Sohn, Jaehoon",
      "full_name": "Jaehoon Sohn",
      "korean_name": "",
      "english_name": "",
      "grade": "12",
      "gender": "Male"
    },
    {
      "student_id": "203",
      "official_name": "Yapjoco, Luigi Marco",
      "full_name": "Luigi Marco Yapjoco",
      "korean_name": "",
      "english_name": "",
      "grade": "12",
      "gender": "Male"
    },
    {
      "student_id": "1057",
      "official_name": "Espe, Victoria Izabel",
      "full_name": "Victoria Izabel Espe",
      "korean_name": "",
      "english_name": "",
      "grade": "8",
      "gender": "Female"
    },
    {
      "student_id": "1095",
      "official_name": "Khatantumur, Elberelt",
      "full_name": "Elberelt Khatantumur",
      "korean_name": "",
      "english_name": "Ebe",
      "grade": "6",
      "gender": "Male"
    },
    {
      "student_id": "1063",
      "official_name": "Lee, Jueun",
      "full_name": "Jueun Lee",
      "korean_name": "",
      "english_name": "",
      "grade": "8",
      "gender": "Female"
    },
    {
      "student_id": "956",
      "official_name": "Co Minh Phuc",
      "full_name": "Co Minh Phuc",
      "korean_name": "",
      "english_name": "Felix",
      "grade": "11",
      "gender": "Male"
    },
    {
      "student_id": "1076",
      "official_name": "Kim, Dami",
      "full_name": "Dami Kim",
      "korean_name": "",
      "english_name": "",
      "grade": "11",
      "gender": "Female"
    },
    {
      "student_id": "1077",
      "official_name": "Kim, Donghan",
      "full_name": "Donghan Kim",
      "korean_name": "",
      "english_name": "Eric",
      "grade": "11",
      "gender": "Male"
    },
    {
      "student_id": "1119",
      "official_name": "Nguyen Gia Bao",
      "full_name": "Nguyen Gia Bao",
      "korean_name": "",
      "english_name": "",
      "grade": "12",
      "gender": "Male"
    }
  ],
  "not_in_masterlist": [
    {
      "id": "71472064-84c8-44d7-a128-31836aef46a4",
      "full_name": "Cho, Soojeong Diaz",
      "english_name": "Soojeong",
      "grade": "6"
    },
    {
      "id": "10cb153f-a753-49eb-a6a9-dadcc17009a9",
      "full_name": "Vhretchard",
      "english_name": "Vhretchard",
      "grade": "6"
    },
    {
      "id": "bcb6152d-e1a8-41e8-8afd-71349d4d4043",
      "full_name": "Headley, Cataleyna Sophia",
      "english_name": "Cataleyna",
      "grade": "7"
    },
    {
      "id": "4b3a7ce3-c6cd-4571-92bf-6b67a10df799",
      "full_name": "Cho, Yeonkyu",
      "english_name": "Yeonkyu",
      "grade": "8"
    },
    {
      "id": "b3efd0a7-e49c-404e-8546-ba9f40710105",
      "full_name": "Gel Emrie Stanley",
      "english_name": "Gel",
      "grade": "8"
    },
    {
      "id": "663de372-a693-4dce-b595-ecc8ebf1b30c",
      "full_name": "Irene Caminero",
      "english_name": "Irene",
      "grade": "8"
    },
    {
      "id": "b3452e39-0470-479e-8c03-d557827fef1f",
      "full_name": "Jon Jacob Smith",
      "english_name": "Jon",
      "grade": "8"
    },
    {
      "id": "54f846a2-6558-418f-b04b-86d7af6c0152",
      "full_name": "Timothy Jefferson P Dayrit",
      "english_name": "Timothy",
      "grade": "8"
    },
    {
      "id": "06fb8e53-fd8b-43d6-a3cc-b61ee125123b",
      "full_name": "John Mirasol",
      "english_name": "John",
      "grade": "11"
    },
    {
      "id": "5f10486c-bb85-43a5-bd19-e01615b64d6f",
      "full_name": "An, Yujun",
      "english_name": "Yujun",
      "grade": "12"
    },
    {
      "id": "16db0e33-0f68-40b8-9027-72e7818bdbdb",
      "full_name": "Jaehoon",
      "english_name": "Jaehoon",
      "grade": "12"
    },
    {
      "id": "3740bcd9-9b8f-43be-ac71-002f16ab6c27",
      "full_name": "Song Sam Dong",
      "english_name": "Dennis",
      "grade": "12"
    }
  ]
}